src/doc-classifier_amira-codecamp/__init__.py
src/doc-classifier_amira-codecamp/doc_classifier.py
doc_classifier_amira_codecamp-0.0.1.dist-info/METADATA
doc_classifier_amira_codecamp-0.0.1.dist-info/WHEEL
doc_classifier_amira_codecamp-0.0.1.dist-info/licenses/LICENSE.md
doc_classifier_amira_codecamp-0.0.1.dist-info/RECORD
