Metadata-Version: 2.1
Name: doc-classifier_amira-codecamp
Version: 0.0.1
Summary: A machine learning model to classify scientific documents (articles & thesis) by field of study
Project-URL: repository, https://github.com/amira-codecamp/doc-classifier
Author: amira-codecamp
License-File: LICENSE.md
Keywords: classification,machine learning,scientific-documents
